<?xml version="1.0"?>
<!-- $Id: dockables.xml 7600 2003-12-30 18:46:24Z orutherfurd $ -->

<!DOCTYPE DOCKABLES SYSTEM "dockables.dtd">

<DOCKABLES>
	<DOCKABLE NAME="perl-dbg-locals" MOVABLE="TRUE">
		new perl.Locals(view);
	</DOCKABLE>
	<DOCKABLE NAME="perl-dbg-watches" MOVABLE="TRUE">
		new perl.Watches(view);
	</DOCKABLE>
	<DOCKABLE NAME="perl-dbg-stack" MOVABLE="TRUE">
		new perl.Stack(view);
	</DOCKABLE>
	<DOCKABLE NAME="perl-dbg-breakpoints" MOVABLE="TRUE">
		new perl.Breakpoints(view);
	</DOCKABLE>
	<DOCKABLE NAME="perl-dbg-panel">
		new perl.ControlPanel(view);
	</DOCKABLE>
	<DOCKABLE NAME="perl-dbg-console">
		new perl.Console(view);
	</DOCKABLE>
</DOCKABLES>

<!-- :noTabs=false:lineSeparator=\r\n:tabSize=4:folding=none: -->
